tsdb/__init__.py
tsdb/config_template.ini
tsdb/data_processing.py
tsdb/database.py
tsdb/version.py
tsdb/loading_funcs/__init__.py
tsdb/loading_funcs/beijing_multisite_air_quality.py
tsdb/loading_funcs/electricity_load_diagrams.py
tsdb/loading_funcs/electricity_transformer_temperature.py
tsdb/loading_funcs/italy_air_quality.py
tsdb/loading_funcs/pems_traffic.py
tsdb/loading_funcs/physionet_2012.py
tsdb/loading_funcs/physionet_2019.py
tsdb/loading_funcs/solar_alabama.py
tsdb/loading_funcs/ucr_uea_datasets.py
tsdb/loading_funcs/vessel_ais.py
tsdb/utils/__init__.py
tsdb/utils/config.py
tsdb/utils/downloading.py
tsdb/utils/file.py
tsdb/utils/logging.py
tsdb-0.7.1.dist-info/LICENSE
tsdb-0.7.1.dist-info/METADATA
tsdb-0.7.1.dist-info/WHEEL
tsdb-0.7.1.dist-info/top_level.txt
tsdb-0.7.1.dist-info/RECORD
