Metadata-Version: 2.2
Name: tsdb
Version: 0.7.1
Summary: TSDB (Time Series Data Beans): a Python toolbox helping load 172 open-source time-series datasets
Author-email: Wenjie Du <wenjay.du@gmail.com>
License: Copyright (c) 2023-present, Wenjie Du
Project-URL: Source, https://github.com/WenjieDu/TSDB
Project-URL: Homepage, https://pypots.com
Project-URL: Documentation, https://docs.pypots.com
Project-URL: Bug Tracker, https://github.com/WenjieDu/TSDB/issues
Project-URL: Download, https://github.com/WenjieDu/TSDB/archive/main.zip
Keywords: data mining,time series,time-series analysis,time-series database,time-series datasets,database,datasets,dataset downloading,imputation,classification,forecasting,partially observed,irregularly sampled,partially-observed time series,incomplete time series,missing data,missing values,pypots
Classifier: Development Status :: 5 - Production/Stable
Classifier: Intended Audience :: Developers
Classifier: Intended Audience :: Education
Classifier: Intended Audience :: Science/Research
Classifier: License :: OSI Approved :: BSD License
Classifier: Operating System :: OS Independent
Classifier: Programming Language :: Python :: 3
Classifier: Topic :: Scientific/Engineering :: Artificial Intelligence
Classifier: Topic :: Software Development :: Libraries :: Application Frameworks
Requires-Python: >=3.8
License-File: LICENSE
Requires-Dist: tqdm
Requires-Dist: numpy
Requires-Dist: scipy
Requires-Dist: pandas
Requires-Dist: pyarrow
Requires-Dist: requests
Requires-Dist: scikit-learn
